{"title":"00. 데이터 가져오기","markdown":{"yaml":{"title":"00. 데이터 가져오기","author":"GC","date":"10/30/23"},"headingText":"Intro","containsRefs":false,"markdown":"\n\n\n`1` 119 병원선정 솔루션 기획\n\n`2` 응급환자의 빠른 병원 이송을 위한 119 구급대원의 병원선정 솔루션 프로토타입 제작\n\n* 이송 중인 환자의 중증질환을 예측하고, 해당 질환에 대해 환자 수용 가능한 병원을 파악하여 `응급실 뺑뺑이`문제 해결\n\n`3` 프로세스\n\n* 공공데이터 수집 및 가공 $\\to$ Featuer 특성 이해 및 최적 모델 찾기 $\\to$ 프로토타입 개발\n\n* 대구광역시 중심으로 데이터 추출\n\n***\n\n# 0. import\n\n* 공공데이터 수집을 위한 기본값 설정\n\n# 1. 대구광역시 응급의료기관 목록정보 조회하기\n\n * 주소 (대구광역시)를 기준으로 응급 의료 기관 목록 정보 조회\n * 기관ID, 주소, 기관명, 응급실전화, 병원 위치(경도/위도) 정보를 확인\n\n# 2. 응급의료기관별 기본정보 조회 - 응급실수, 수술실 수 확인\n\n * <b>기관ID</b>를 기준으로 응급실, 수술실 정보 등 응급의료기관 기본 정보 조회 가능\n * 응급실수 (hperyn)와 수술실 수(hpopyn) 정보를 확인\n\n# 3. 응급의료기관별 실시간 가용 병상 조회\n\n * 주소(대구광역시)를 기준으로 응급실 실시간 가용병상정보 등을 조회\n * 실시간 응급실(hvec), 수술실(hvoc) 가용 수량 정보 확인\n\n# 4. 응급의료기관별 중증질환자 수용 가능 여부 조회\n\n * 주소(대구광역시)를 기준으로 중증질환자 수용 가능 여부를 조회 (실시간 정보)\n\n# 5. 자료 정비하기\n\n * 컬럼명 한글로 변경하기\n * 데이터 중 '정보 미제공', '불가능'은 'N'로 변경\n * 응급실/수술실 수가 0 이하의 수치가 나오는 비정상 사례 존재 --> 0이하의 수치는 모두 0으로 대체하여 정비\n * 응급실 가용율 (응급실 가용 수량 / 응급실수)을 계산\n * 응급실 포화도는 응급실 가용율에 따라 [불가/혼잡/보통/원활] 4단계로 구분\n\n# 6. 상황에 따른 병원 데이터 출력하기\n\n * 상황1) 응급실 수용이 가능한 병원\n * 상황2) 중증질환자 수용이 가능하고 응급실 수용이 가능한 병원\n\n# 7. 병원 거리 구하기\n\n * 병원 위치(위도/경도)와 환자의 위치(임의의 위도/경도) 간의 거리 측정\n * haversine 라이브러리를 활용 (https://pypi.org/project/haversine/)\n * 병원 ~ 환자간의 거리를 ['2km이내', '5km이내', '10km이내', '10km이상'] 4단계로 구분\n\n# 8. 중증 질환자를 수용 가능한 응급의료기관을 가까운 거리순으로 출력\n\n# 9. 특정 중증질환 및 환자 위치에 따른 병원 실시간 정보 및 거리를 구하는 함수 작성하기\n\n * 작성 방법\n    * 1) 함수선언하기\n    * 2) 병원 리스트 csv 파일 불러오기\n    * 3) 병원 실시간 정보 가져오기\n    * 4) 병원 응급실 가용율, 포화도 계산하기\n    * 5) 환자 수용 가능한 병원 구하기 \n    * 6) 환자와 병원간 거리 구하기\n    * 7) 거리 구간 구하기\n    * 8) 결과값 반환하기\n\n# 9. folium\n\n`-` 환자 위치정보를 중심을 지도위에 marker로 표시하고 가장 가까운 병원을 찾아보자.\n\n## (1) 위도, 경도 파일 읽어오기\n\n## (2) 대구광역시를 찾아보자\n\n`-` 대충 어떤 구조인지 파악\n","srcMarkdownNoYaml":"\n\n# Intro\n\n`1` 119 병원선정 솔루션 기획\n\n`2` 응급환자의 빠른 병원 이송을 위한 119 구급대원의 병원선정 솔루션 프로토타입 제작\n\n* 이송 중인 환자의 중증질환을 예측하고, 해당 질환에 대해 환자 수용 가능한 병원을 파악하여 `응급실 뺑뺑이`문제 해결\n\n`3` 프로세스\n\n* 공공데이터 수집 및 가공 $\\to$ Featuer 특성 이해 및 최적 모델 찾기 $\\to$ 프로토타입 개발\n\n* 대구광역시 중심으로 데이터 추출\n\n***\n\n# 0. import\n\n* 공공데이터 수집을 위한 기본값 설정\n\n# 1. 대구광역시 응급의료기관 목록정보 조회하기\n\n * 주소 (대구광역시)를 기준으로 응급 의료 기관 목록 정보 조회\n * 기관ID, 주소, 기관명, 응급실전화, 병원 위치(경도/위도) 정보를 확인\n\n# 2. 응급의료기관별 기본정보 조회 - 응급실수, 수술실 수 확인\n\n * <b>기관ID</b>를 기준으로 응급실, 수술실 정보 등 응급의료기관 기본 정보 조회 가능\n * 응급실수 (hperyn)와 수술실 수(hpopyn) 정보를 확인\n\n# 3. 응급의료기관별 실시간 가용 병상 조회\n\n * 주소(대구광역시)를 기준으로 응급실 실시간 가용병상정보 등을 조회\n * 실시간 응급실(hvec), 수술실(hvoc) 가용 수량 정보 확인\n\n# 4. 응급의료기관별 중증질환자 수용 가능 여부 조회\n\n * 주소(대구광역시)를 기준으로 중증질환자 수용 가능 여부를 조회 (실시간 정보)\n\n# 5. 자료 정비하기\n\n * 컬럼명 한글로 변경하기\n * 데이터 중 '정보 미제공', '불가능'은 'N'로 변경\n * 응급실/수술실 수가 0 이하의 수치가 나오는 비정상 사례 존재 --> 0이하의 수치는 모두 0으로 대체하여 정비\n * 응급실 가용율 (응급실 가용 수량 / 응급실수)을 계산\n * 응급실 포화도는 응급실 가용율에 따라 [불가/혼잡/보통/원활] 4단계로 구분\n\n# 6. 상황에 따른 병원 데이터 출력하기\n\n * 상황1) 응급실 수용이 가능한 병원\n * 상황2) 중증질환자 수용이 가능하고 응급실 수용이 가능한 병원\n\n# 7. 병원 거리 구하기\n\n * 병원 위치(위도/경도)와 환자의 위치(임의의 위도/경도) 간의 거리 측정\n * haversine 라이브러리를 활용 (https://pypi.org/project/haversine/)\n * 병원 ~ 환자간의 거리를 ['2km이내', '5km이내', '10km이내', '10km이상'] 4단계로 구분\n\n# 8. 중증 질환자를 수용 가능한 응급의료기관을 가까운 거리순으로 출력\n\n# 9. 특정 중증질환 및 환자 위치에 따른 병원 실시간 정보 및 거리를 구하는 함수 작성하기\n\n * 작성 방법\n    * 1) 함수선언하기\n    * 2) 병원 리스트 csv 파일 불러오기\n    * 3) 병원 실시간 정보 가져오기\n    * 4) 병원 응급실 가용율, 포화도 계산하기\n    * 5) 환자 수용 가능한 병원 구하기 \n    * 6) 환자와 병원간 거리 구하기\n    * 7) 거리 구간 구하기\n    * 8) 결과값 반환하기\n\n# 9. folium\n\n`-` 환자 위치정보를 중심을 지도위에 marker로 표시하고 가장 가까운 병원을 찾아보자.\n\n## (1) 위도, 경도 파일 읽어오기\n\n## (2) 대구광역시를 찾아보자\n\n`-` 대충 어떤 구조인지 파악\n"},"formats":{"html":{"identifier":{"display-name":"HTML","target-format":"html","base-format":"html"},"execute":{"fig-width":7,"fig-height":5,"fig-format":"retina","fig-dpi":96,"df-print":"default","error":false,"eval":true,"cache":null,"freeze":true,"echo":true,"output":true,"warning":true,"include":true,"keep-md":false,"keep-ipynb":false,"ipynb":null,"enabled":false,"daemon":null,"daemon-restart":false,"debug":false,"ipynb-filters":[],"ipynb-shell-interactivity":null,"plotly-connected":true,"engine":"jupyter"},"render":{"keep-tex":false,"keep-typ":false,"keep-source":false,"keep-hidden":false,"prefer-html":false,"output-divs":true,"output-ext":"html","fig-align":"default","fig-pos":null,"fig-env":null,"code-fold":false,"code-overflow":"scroll","code-link":false,"code-line-numbers":true,"code-tools":false,"tbl-colwidths":"auto","merge-includes":true,"inline-includes":false,"preserve-yaml":false,"latex-auto-mk":true,"latex-auto-install":true,"latex-clean":true,"latex-min-runs":1,"latex-max-runs":10,"latex-makeindex":"makeindex","latex-makeindex-opts":[],"latex-tlmgr-opts":[],"latex-input-paths":[],"latex-output-dir":null,"link-external-icon":false,"link-external-newwindow":false,"self-contained-math":false,"format-resources":[],"notebook-links":true},"pandoc":{"standalone":true,"wrap":"none","default-image-extension":"png","to":"html","css":["../../../styles.css"],"toc":true,"output-file":"2023-10-30-00. 데이터 가져오기.html"},"language":{"toc-title-document":"Table of contents","toc-title-website":"On this page","related-formats-title":"Other Formats","related-notebooks-title":"Notebooks","source-notebooks-prefix":"Source","other-links-title":"Other Links","code-links-title":"Code Links","launch-dev-container-title":"Launch Dev Container","launch-binder-title":"Launch Binder","article-notebook-label":"Article Notebook","notebook-preview-download":"Download Notebook","notebook-preview-download-src":"Download Source","notebook-preview-back":"Back to Article","manuscript-meca-bundle":"MECA Bundle","section-title-abstract":"Abstract","section-title-appendices":"Appendices","section-title-footnotes":"Footnotes","section-title-references":"References","section-title-reuse":"Reuse","section-title-copyright":"Copyright","section-title-citation":"Citation","appendix-attribution-cite-as":"For attribution, please cite this work as:","appendix-attribution-bibtex":"BibTeX citation:","title-block-author-single":"Author","title-block-author-plural":"Authors","title-block-affiliation-single":"Affiliation","title-block-affiliation-plural":"Affiliations","title-block-published":"Published","title-block-modified":"Modified","title-block-keywords":"Keywords","callout-tip-title":"Tip","callout-note-title":"Note","callout-warning-title":"Warning","callout-important-title":"Important","callout-caution-title":"Caution","code-summary":"Code","code-tools-menu-caption":"Code","code-tools-show-all-code":"Show All Code","code-tools-hide-all-code":"Hide All Code","code-tools-view-source":"View Source","code-tools-source-code":"Source Code","tools-share":"Share","tools-download":"Download","code-line":"Line","code-lines":"Lines","copy-button-tooltip":"Copy to Clipboard","copy-button-tooltip-success":"Copied!","repo-action-links-edit":"Edit this page","repo-action-links-source":"View source","repo-action-links-issue":"Report an issue","back-to-top":"Back to top","search-no-results-text":"No results","search-matching-documents-text":"matching documents","search-copy-link-title":"Copy link to search","search-hide-matches-text":"Hide additional matches","search-more-match-text":"more match in this document","search-more-matches-text":"more matches in this document","search-clear-button-title":"Clear","search-text-placeholder":"","search-detached-cancel-button-title":"Cancel","search-submit-button-title":"Submit","search-label":"Search","toggle-section":"Toggle section","toggle-sidebar":"Toggle sidebar navigation","toggle-dark-mode":"Toggle dark mode","toggle-reader-mode":"Toggle reader mode","toggle-navigation":"Toggle navigation","crossref-fig-title":"Figure","crossref-tbl-title":"Table","crossref-lst-title":"Listing","crossref-thm-title":"Theorem","crossref-lem-title":"Lemma","crossref-cor-title":"Corollary","crossref-prp-title":"Proposition","crossref-cnj-title":"Conjecture","crossref-def-title":"Definition","crossref-exm-title":"Example","crossref-exr-title":"Exercise","crossref-ch-prefix":"Chapter","crossref-apx-prefix":"Appendix","crossref-sec-prefix":"Section","crossref-eq-prefix":"Equation","crossref-lof-title":"List of Figures","crossref-lot-title":"List of Tables","crossref-lol-title":"List of Listings","environment-proof-title":"Proof","environment-remark-title":"Remark","environment-solution-title":"Solution","listing-page-order-by":"Order By","listing-page-order-by-default":"Default","listing-page-order-by-date-asc":"Oldest","listing-page-order-by-date-desc":"Newest","listing-page-order-by-number-desc":"High to Low","listing-page-order-by-number-asc":"Low to High","listing-page-field-date":"Date","listing-page-field-title":"Title","listing-page-field-description":"Description","listing-page-field-author":"Author","listing-page-field-filename":"File Name","listing-page-field-filemodified":"Modified","listing-page-field-subtitle":"Subtitle","listing-page-field-readingtime":"Reading Time","listing-page-field-wordcount":"Word Count","listing-page-field-categories":"Categories","listing-page-minutes-compact":"{0} min","listing-page-category-all":"All","listing-page-no-matches":"No matching items","listing-page-words":"{0} words"},"metadata":{"lang":"en","fig-responsive":true,"quarto-version":"1.4.549","theme":{"light":"cosmos"},"editor":"visual","code-copy":true,"title-block-banner":true,"title":"00. 데이터 가져오기","author":"GC","date":"10/30/23"},"extensions":{"book":{"multiFile":true}}}},"projectFormats":["html"]}